Workbook
Name Intitules_BiensEssentiels: #REF!
Name Intitules_BiensSupports: #REF!
Name Refs_BiensEssentiels: #REF!
Name Refs_BiensSupports: #REF!
Name Refs_EvenementsRedoutes: #REF!
Name Refs_ScenariosDeMenace: #REF!

Sheet Organisation
A1: EBIOS RISK MANAGER | B1: DSI | C1: RSSI | D1: Métier | E1: Direction | F1: Spécialiste Threat Intel | G1: Architecte fonctionnel | H1: Architecte technique
A2: Atelier 1 | B2: C | C2: R | D2: C | E2: A | F2: I | G2: C | H2: C
A3: Atelier 2 | B3: I | C3: R | D3: C | E3: A | F3: C | G3: I | H3: I
A4: Atelier 3 | B4: C | C4: R | D4: C | E4: A | F4: C | G4: C | H4: C
A5: Atelier 4 | B5: C | C5: R | D5: I | E5: I | F5: C | G5: C | H5: C
A6: Atelier 5 | B6: C | C6: R | D6: C | E6: A | F6: I | G6: C | H6: C
A8: Objet de l’étude : plateforme cloud hébergeant l’ERP et le CRM de Rhénalis SAS (cas fictif) — postes, serveurs d’application, base de données, annuaire, sauvegardes, infogérance.
A9: Cadre temporel : étude d’octobre 2026 ; cycle stratégique tous les 3 ans, cycle opérationnel annuel ; plan de traitement sur 12 mois.
A10: Participants : Claire Muller (Direction), Sophie Haas (DSI et RSSI), Thomas Weber et Julien Roth (Métier), Laura Meyer (Architecte fonctionnel), InfoGest Services (Architecte technique), le groupe d’étudiants (Threat Intel, conseil SSI).
A11: Note : Sophie Haas cumule les fonctions DSI et RSSI ; la matrice décrit le rôle de chaque fonction, pas des personnes distinctes.
A12: Légende : R = réalise, A = approuve, C = consulté, I = informé.

Sheet Métriques
A2: Besoins de sécurité | G2: Gravité | J2: Vraissemblance | Z2: Cotation des critères de menaces des parties prenantes
A3: Niveau | B3: Disponibilité | C3: Intégrité | D3: Confidentialité | E3: Tracabilité | F3: Besoins de sécurité | G3: G4 | H3: Incapacité pour la société d’assurer tout ou partie de son activité, avec d’éventuels impacts graves sur la sécurité des personnes et des biens. La société ne surmontera vraisemblablement pas la situation (sa survie est menacée). | I3: Gravité | J3: 1 | K3: La source de risque a très peu de chance d'atteindre son objectif visé en empruntant un des modes opératoires. | R3: Vraissemblance | T3: Niveau | U3: Niveau de risque | Y3: Evaluation du risque | Z3: Niveau | AA3: Dépendance | AB3: Pénétration | AC3: Maturité SSI | AD3: Confiance | AE3: Parties prenantes | AG3: Niveau | AH3: Description | AL3: Couples SROV
A4: 1 | B4: Pas de disponibilité requise | C4: Pas d'intégrité nécéssaire | D4: Le bien est accessible publiquement | E4: Pas de tracabilité nécéssaire | G4: G3 | H4: Forte dégradation des performances de l’activité, avec d’éventuels impacts significatifs sur la sécurité des personnes et des biens. La société surmontera la situation avec de sérieuses difficultés (fonctionnement en mode très dégrade). | J4: 2 | K4: La source de risqueest susceptible d'atteindre son objectif visé en empruntant un des modes opératoires. | T4: 1 | U4: Faible | Z4: 1 | AA4: Relation non nécessaire aux fonctions stratégiques | AB4: Pas d’accès ou accès avec privilèges de type utilisateur à des terminaux utilisateurs (poste de travail, ordiphone, etc.). | AC4: Des règles d’hygiène sont appliquées ponctuellement et non formalisées. La capacité de réaction sur incident est incertaine. | AD4: Les intentions de la partie prenante ne peuvent être évaluées. | AG4: 1 | AH4: Faible
A5: 2 | B5: Le bien ne peut être indisponible plus d'une semaine | C5: L'intégrité doit être connue | D5: L'accès doit être limité aux employés uniquement | E5: Tracabilité nécéssaire pour des besoins de qualité ou techniques | G5: G2 | H5: Dégradation des performances de l’activité sans impact sur la sécurité des personnes et des biens. La société surmontera la situation malgré quelques difficultés (fonctionnement en mode dégrade). | J5: 3 | K5: La source de risque va probalement atteindre son objectif visé en empruntant un des modes opératoires. | T5: 2 | U5: Significatif | Z5: 2 | AA5: Relation utile aux fonctions stratégiques | AB5: Accès avec privilèges de type administrateur à des terminaux utilisateurs (parc informatique, flotte de terminaux mobiles, etc.) ou accès physique aux sites de l’organisation. | AC5: Les règles d’hygiène et la réglementation sont prises en compte, sans intégration dans une politique globale. La sécurité numérique est conduite selon un mode réactif. | AD5: Les intentions de la partie prenante sont considérées comme neutres. | AG5: 2 | AH5: Moyen
A6: 3 | B6: Le bien ne peut être indisponible plus d'une journée | C6: L'intégrité doit être connue et récupérable | D6: L'accès doit être limité à un groupe restreint d'employés uniquement | E6: Tracabilité nécéssaire pour des besoins métiers ou contractuels | G6: G1 | H6: Aucun impact opérationnel ni sur les performances de l’activité ni sur la sécurité des personnes et des biens. La société surmontera la situation sans trop de difficultés (consommation des marges). | J6: 4 | K6: La source de risque va certainement atteindre son objectif visé en empruntant un des modes opératoires. | T6: 3 | U6: Modéré | Z6: 3 | AA6: Relation indispensable mais non exclusive | AB6: Accès avec privilèges de type administrateur à des serveurs « métier » (serveur de fichiers, bases de données, serveur web, serveur d’application, etc.). | AC6: Une politique globale est appliquée en matière de sécurité numérique. Celle-ci est assurée selon un mode réactif, avec une recherche de centralisation et d’anticipation sur certains risques. | AD6: Les intentions de la partie prenante sont connues et probablement positives. | AG6: 3 | AH6: Elevé
A7: 4 | B7: Le bien ne peut être indisponible plus d'une heure | C7: L'intégrité doit être garantie | D7: L'accès doit être interdit pour tous. | E7: Tracabilité nécéssaire pour des besoins légaux ou reglementaires | T7: 4 | U7: Elevé | Z7: 4 | AA7: Relation indispensable et unique (pas de substitution possible à court terme) | AB7: Accès avec privilèges de type administrateur à des équipements d’infrastructure (annuaires, DNS, DHCP, commutateurs, pare-feu, hyperviseurs, baies de stockage, etc.) ou accès physique aux salles serveurs de l’organisation. | AC7: La partie prenante met en oeuvre une politique de management du risque. La politique est intégrée et prend pleinement en compte une dimension proactive. | AD7: Les intentions de la partie prenante sont parfaitement connues et pleinement compatibles avec celles de l’organisation étudiée.
L10: Vraissemblance | N10: Facilité d'exploitation | S10: Niveau de risque | U10: Vraissemblance | AF10: Pertinence | AH10: Motivation
N11: 1 | O11: 2 | P11: 3 | Q11: 4 | U11: 1 | V11: 2 | W11: 3 | X11: 4 | AH11: + | AI11: ++ | AJ11: +++
L12: Probabilité | M12: 1 | N12: 1 | O12: 2 | P12: 2 | Q12: 3 | S12: Gravité | T12: 1 | U12: 1 | V12: 2 | W12: 2 | X12: 3 | AF12: Ressources | AG12: +++ | AH12: Moyen | AI12: Elevé | AJ12: Elevé
M13: 2 | N13: 2 | O13: 2 | P13: 3 | Q13: 3 | T13: 2 | U13: 2 | V13: 2 | W13: 3 | X13: 3 | AG13: ++ | AH13: Faible | AI13: Moyen | AJ13: Elevé
M14: 3 | N14: 2 | O14: 3 | P14: 3 | Q14: 4 | T14: 3 | U14: 2 | V14: 3 | W14: 3 | X14: 4 | AG14: + | AH14: Faible | AI14: Faible | AJ14: Moyen
M15: 4 | N15: 3 | O15: 3 | P15: 4 | Q15: 4 | T15: 4 | U15: 3 | V15: 3 | W15: 4 | X15: 4

Sheet Atelier 1 - Missions
A1: Missions | B1: Rhénalis SAS (cas fictif) : vendre, livrer et facturer du matériel électrique aux professionnels du Grand Est
A2: Dénomination de la valeur métier | B2: VM1 - Prise et traitement des commandes clients | G2: VM2 - Fichier clients et prospects | H2: VM3 - Facturation et recouvrement | J2: VM4 - Données comptables et financières | M2: VM5 - Gestion des stocks et approvisionnements
A3: Nature de la valeur métier(processus ou information) | B3: processus | G3: information | H3: processus | J3: information | M3: processus
A4: Description | B4: Saisie des commandes (téléphone, e-mail, commerciaux), contrôle du stock et du crédit client, préparation et expédition. Environ 70 % du chiffre d'affaires transite par ce processus. Engagement de livraison J+1 sur le stock auprès des grands comptes (hypothèse H02/H03). | G4: Coordonnées, historique d'achats, conditions tarifaires négociées, devis et opportunités de ~3 500 comptes professionnels. Contient des données personnelles (RGPD) et des informations commercialement sensibles. | H4: Émission des factures à partir des commandes livrées, envoi aux clients, suivi des encaissements et relances. Soumis aux obligations fiscales et à la réforme de la facturation électronique. | J4: Écritures comptables, grand livre, comptes clients et fournisseurs, trésorerie. Intégrité et conservation légale de 10 ans exigées ; base des déclarations fiscales et des comptes annuels. | M4: Suivi des niveaux de stock des 2 dépôts (Colmar, Mulhouse), réapprovisionnement, commandes fournisseurs et réception des marchandises.
A5: Entité ou personne responsable(INTERNE/EXTERNE) | B5: VM1 et VM2 : Julien Roth, directeur commercial (INTERNE) | VM3 et VM4 : Thomas Weber, DAF (INTERNE) | VM5 : responsable logistique, nom à préciser (INTERNE)
A6: Dénomination du/des biens supports associés | B6: Module Ventes de l'ERP | C6: Postes de travail de l'ADV | D6: Serveurs d'application ERP/CRM (IaaS) | G6: Application CRM et portables des commerciaux | H6: Module Facturation de l'ERP et plateforme de facturation électronique | I6: Annuaire Active Directory (comptes et droits) | J6: Base de données ERP/CRM | K6: Système de sauvegarde | L6: Accès distant d'administration de l'infogérant | M6: Modules Stocks et Achats de l'ERP | N6: Postes de l'entrepôt
A7: Description | B7: Logiciel : saisie et suivi des commandes, contrôle stock et encours. | C7: Matériel : ~10 postes Windows du service administration des ventes, accès à l'ERP via le VPN site à site. | D7: Infrastructure : machines virtuelles hébergeant l'ERP et le CRM chez un hébergeur IaaS français. Partagé par toutes les VM. | G7: Logiciel CRM + 12 portables nomades connectés en VPN. | H7: Logiciel : génération et émission des factures, connecteur vers la plateforme de dématérialisation (hypothèse). | I7: Logiciel : authentification de tous les utilisateurs et administrateurs. Bien support transverse. | J7: Logiciel : SGBD stockant les données ERP et CRM. Transverse. | K7: Logiciel/stockage : sauvegardes quotidiennes déclarées (H06), non testées (H07). Transverse. | L7: Organisation : VPN d'administration, sans MFA supposé (H04), compte admin partagé (H05). Transverse. | M7: Logiciel : niveaux de stock, réassort, commandes fournisseurs. | N7: Matériel : postes de réception et préparation des 2 dépôts.
A8: Entité ou personne responsable(INTERNE/EXTERNE) | B8: Sophie Haas, resp. informatique (INTERNE) | C8: Sophie Haas (INTERNE) | D8: InfoGest Services (EXTERNE) | G8: Sophie Haas (INTERNE) | H8: Sophie Haas (INTERNE) | I8: InfoGest Services (EXTERNE) | J8: InfoGest Services (EXTERNE) | K8: InfoGest Services (EXTERNE) | L8: InfoGest Services (EXTERNE) | M8: Sophie Haas (INTERNE) | N8: Sophie Haas (INTERNE)
A10: Biens supports complémentaires | B10: Type | C10: Responsable - valeurs métier
A11: Postes de la comptabilité | B11: Matériel | C11: Sophie Haas (INTERNE) - VM3, VM4
A12: Console d’administration IaaS | B12: Logiciel | C12: InfoGest Services / hébergeur (EXTERNE) - toutes
A13: Accès de télémaintenance de l’éditeur | B13: Organisation | C13: Éditeur de l’ERP (EXTERNE) - VM1, VM3, VM5
A14: Personnel (utilisateurs et administrateurs) | B14: Personnes | C14: Direction (INTERNE) - toutes
A15: Liaisons VPN (site à site et nomades) | B15: Réseau | C15: InfoGest Services (EXTERNE) - toutes
A16: Messagerie (SaaS) | B16: Logiciel | C16: Fournisseur de messagerie (EXTERNE) - VM1, VM3

Sheet Atelier 1 - ER
A1: Identification | C1: Cotation
A2: Valeur métier | B2: Evenement redouté | C2: Impact | D2: Gravité | E2: Besoin D-I-C-T | F2: Justification
A3: VM1 - Prise et traitement des commandes clients | B3: Impossibilité de prendre et traiter les commandes pendant plus d'une semaine (ERP indisponible, par exemple après un chiffrement par rançongiciel) | C3: Arrêt d'environ 70 % des ventes, soit ~300 k€ de CA par semaine (70 % × 22 M€ / 52). Engagements de livraison J+1 non tenus, pénalités et perte de grands comptes au profit de concurrents. Mode dégradé papier tenable 1 journée seulement (H03). La société survit mais avec de sérieuses difficultés. | D3: G3 | E3: D3 | F3: Le mode dégradé ne tient qu'une journée (H03)
A4: VM1 - Prise et traitement des commandes clients | B4: Altération des commandes en cours (quantités, prix, adresses de livraison modifiés) | C4: Erreurs de livraison et de facturation, retours et litiges, temps de contrôle manuel. Erreurs détectables et corrigeables : dégradation de l'activité sans mise en danger de la société. | D4: G2 | E4: I3 | F4: Une altération doit être connue et récupérable
A5: VM2 - Fichier clients et prospects | B5: Vol et divulgation du fichier clients et prospects (exfiltration puis revente ou publication) | C5: Violation de données personnelles : notification à la CNIL sous 72 h, sanction possible. Tarifs négociés exposés aux concurrents, perte de confiance des clients et démarchage ciblé par la concurrence. Atteinte durable à l'image et à la position commerciale. | D5: G3 | E5: C3 | F5: Accès réservé à la direction commerciale
A6: VM3 - Facturation et recouvrement | B6: Interruption de l'émission des factures et du suivi des encaissements pendant plus de 2 semaines | C6: Retard d'encaissement d'environ 850 k€ (2 semaines de CA), tension de trésorerie. Non-respect possible des obligations de facturation. Les factures sont décalées et non perdues : rattrapage possible, mode dégradé. | D6: G2 | E6: D2 | F6: Rattrapage possible : une semaine tenable
A7: VM3 - Facturation et recouvrement | B7: Modification frauduleuse des coordonnées bancaires sur les factures émises (fraude au RIB) | C7: Paiements clients détournés vers le compte de l'attaquant, potentiellement plusieurs centaines de k€ avant détection. Litiges avec les clients qui ont payé de bonne foi, perte financière souvent non récupérable. | D7: G3 | E7: I4 | F7: L'intégrité du RIB doit être garantie
A8: VM4 - Données comptables et financières | B8: Perte définitive des données comptables et de gestion (base de données chiffrée ou détruite, sauvegardes inutilisables) | C8: Impossible de reconstituer les comptes clients, les encours, les stocks et la comptabilité. Manquement à l'obligation légale de conservation (10 ans), comptes annuels non établis, créances non recouvrables. Survie de la société menacée. Cotation dépendante de H07-H08 (aucun test de restauration documenté, pas de copie hors ligne). | D8: G4 | E8: I4 + T4 | F8: Intégrité garantie et traçabilité légale (conservation 10 ans)
A9: VM5 - Gestion des stocks et approvisionnements | B9: Indisponibilité de la gestion des stocks et des commandes fournisseurs pendant plus de 3 jours | C9: Ruptures de stock, réapprovisionnements bloqués, inventaire manuel des 2 dépôts. Retards de livraison mais activité maintenue en mode dégradé. | D9: G2 | E9: D2 | F9: Inventaire manuel possible quelques jours ; au-delà d'une semaine, ruptures

Sheet Atelier 1 - GAP
A1: Identification | C1: Cotation
A2: Type de référentiel | B2: Nom du referentiel | C2: Etat d'application | D2: Ecarts | E2: Justification des écarts
A3: Bonnes pratiques | B3: Guide d'hygiène informatique ANSSI (42 mesures) | C3: Partiellement appliqué | D3: Pas d'authentification multifacteur sur les accès distants d'administration (VPN de l'infogérant) ni sur la messagerie | E3: Hypothèse H04. Configuration historique de l'infogérant, jamais remise en cause ; aucune exigence MFA dans le contrat.
A4: Bonnes pratiques | B4: Guide d'hygiène informatique ANSSI (42 mesures) | C4: Partiellement appliqué | D4: Compte administrateur de domaine partagé entre les techniciens de l'infogérant, non nominatif | E4: Hypothèse H05. Facilité d'exploitation pour l'infogérant ; empêche toute traçabilité des actions d'administration.
A5: Bonnes pratiques | B5: Guide d'hygiène informatique ANSSI (42 mesures) | C5: Partiellement appliqué | D5: Aucun test de restauration documenté ; pas de copie hors ligne ou immuable | E5: Fréquence quotidienne à confirmer auprès de l'infogérant (H06) ; aucun compte rendu de test (H07, information manquante) ; copie sur la même infrastructure (H08). Coût d'une copie externalisée jamais budgété.
A6: Bonnes pratiques | B6: Guide d'hygiène informatique ANSSI (42 mesures) | C6: Partiellement appliqué | D6: Pas de solution de détection sur les postes (EDR), antivirus classique uniquement | E6: Hypothèse H09. Budget sécurité limité, pas de personnel pour exploiter les alertes.
A7: Bonnes pratiques | B7: Guide d'hygiène informatique ANSSI (42 mesures) | C7: Non appliqué | D7: Pas de journalisation centralisée ni de supervision de sécurité | E7: Hypothèse H11. Aucun SIEM ni SOC ; journaux conservés localement sur chaque serveur.
A8: Bonnes pratiques | B8: Guide d'hygiène informatique ANSSI (42 mesures) | C8: À vérifier | D8: Application des correctifs sur les postes déclarée mensuelle, sans preuve | E8: Hypothèse H10 (déclaration à recueillir auprès du responsable informatique) : à confirmer par un export de la console de mise à jour. Correctifs des serveurs : responsabilité de l'infogérant, non documentée.
A9: Bonnes pratiques | B9: Guide d'hygiène informatique ANSSI (42 mesures) | C9: Non appliqué | D9: Pas de politique de sécurité (PSSI) ni de plan de continuité et de reprise (PCA/PRA) | E9: Hypothèse H12. Pas de RSSI dédié, sujet jamais porté par la direction.
A10: Bonnes pratiques | B10: Guide d'hygiène informatique ANSSI (42 mesures) | C10: Partiellement appliqué | D10: Droits d'accès au CRM trop larges : tous les commerciaux peuvent exporter l'ensemble du fichier clients ; aucun contrôle des exports ni des supports USB | E10: Hypothèses H19 et H21. Paramétrage par défaut du CRM, pas de revue périodique des droits.
A11: Réglementation | B11: RGPD (règlement UE 2016/679) | C11: Partiellement appliqué | D11: Registre des traitements incomplet pour le CRM ; pas de procédure de notification de violation à la CNIL sous 72 h | E11: Hypothèse H16. Pas de DPO désigné, sujet traité ponctuellement par le DAF.
A12: Réglementation | B12: Code de commerce et Livre des procédures fiscales (conservation des pièces comptables 10 ans) | C12: Appliqué sous réserve | D12: La conservation légale repose sur des sauvegardes sans test de restauration documenté | E12: Conformité théorique, non démontrée tant qu'aucun test de restauration n'est réalisé (H07).
A13: Contrat | B13: Contrat d'infogérance InfoGest Services | C13: Partiellement appliqué | D13: Aucune clause de sécurité : ni exigences techniques, ni droit d'audit, ni délai de notification d'incident | E13: Hypothèse H13. Contrat ancien centré sur la disponibilité ; jamais renégocié.
... A15: Procédure interne | B15: Contrôle interne (procédures financières) | C15: Non appliqué | D15: Aucune procédure de vérification des changements de RIB (ni contre-appel, ni double validation) ; clients jamais informés du risque de fraude | E15: Hypothèse H20. Changements de RIB traités sur simple courriel.

Sheet Atelier 2 - SROV
A1: Identification | C1: Cotation | E1: Evaluation
A2: Sources de risque | B2: Objectifs visés | C2: Motivation | D2: Ressources | E2: Pertinence du couple SR/OV | F2: Priorité | G2: Retenu | H2: Justification de l'exclusion du couple SR/OV
A3: SR1 - Organisation criminelle (rançongiciel) | B3: OV1 - Gain financier : chiffrer l'ERP/CRM et les sauvegardes puis exiger une rançon, avec exfiltration préalable des données pour double extorsion (ER : ERP indisponible G3, perte des données G4, vol du fichier clients G3) | C3: +++ | D3: ++ | E3: Elevée | F3: 1 | G3: OUI
A4: SR2 - Organisation criminelle (fraude financière) | B4: OV2 - Gain financier : détourner les paiements clients par fraude au RIB, après compromission d'une messagerie ou d'un compte ERP (ER : fraude au RIB G3) | C4: +++ | D4: + | E4: Moyenne | F4: 2 | G4: OUI
A5: SR3 - Collaborateur malveillant (commercial sur le départ) | B5: OV3 - Lucratif / avantage personnel : emporter le fichier clients et les tarifs négociés chez un concurrent ou pour une future activité (ER : vol du fichier clients G3) | C5: ++ | D5: ++ | E5: Moyenne | F5: 2 | G5: OUI
A6: SR4 - Concurrent | B6: OV4 - Espionnage : obtenir le fichier clients et la politique tarifaire de Rhénalis | C6: ++ | D6: + | E6: Faible | F6: 0 | G6: NON | H6: Concurrents régionaux de taille comparable, sans capacité offensive et exposés à un risque pénal. Le scénario réaliste passe par un salarié débauché : il est couvert par SR3/OV3.
A7: SR5 - Organisation étatique | B7: OV5 - Espionnage ou prépositionnement stratégique | C7: + | D7: +++ | E7: Moyenne | F7: 0 | G7: NON | H7: Pertinence théorique moyenne (ressources maximales) mais aucune motivation : Rhénalis n'a ni activité stratégique, ni données sensibles pour un État, ni client sensible. Exclu par décision du groupe.
A8: SR6 - Activiste | B8: OV6 - Idéologique : nuire à l'image de l'entreprise ou perturber son activité | C8: + | D8: ++ | E8: Faible | F8: 0 | G8: NON | H8: Aucune activité controversée (distribution de matériel électrique). Pas de motivation identifiée.
A9: SR7 - Amateur (script-kiddie) | B9: OV7 - Défi / amusement : perturber un service exposé sur Internet | C9: + | D9: + | E9: Faible | F9: 0 | G9: NON | H9: Plateforme ERP/CRM non exposée publiquement (accès par VPN), site vitrine hors périmètre. Menace couverte par le socle de sécurité (atelier 1 - GAP).
A10: SR8 - Collaborateur mécontent (licencié) | B10: OV8 - Vengeance : saboter les données ou l'ERP | C10: ++ | D10: + | E10: Faible | F10: 0 | G10: NON | H10: Droits utilisateurs limités, pas d'accès administrateur. Risque traité par le socle : retrait des accès au départ, sauvegardes.

Sheet Atelier 3 - PP
A1: Catégories | B1: Parties prenantes | C1: Dépendance | D1: Pénétration | E1: Maturité | F1: Confiance | G1: Exposition | H1: Niveau SSI | I1: Indice de menace | J1: Justification de la cotation
A2: Prestataire | B2: InfoGest Services - infogérant (serveurs, annuaire, sauvegardes) | C2: 4 | D2: 4 | E2: 2 | F2: 2 | G2: =C2*D2 -> 16 | H2: =E2*F2 -> 4 | I2: =G2/H2 -> 4 | J2: Dép. 4 : seul à administrer la plateforme. Pén. 4 : admin du domaine, des serveurs et des sauvegardes. Mat. 2 : sécurité réactive, compte partagé, pas de MFA (H04, H05). Conf. 2 : contrat sans clause de sécurité (H13).
A3: Fournisseur | B3: Hébergeur IaaS (machines virtuelles, stockage, réseau) | C3: 4 | D3: 4 | E3: 3 | F3: 3 | G3: =C3*D3 -> 16 | H3: =E3*F3 -> 9 | I3: =G3/H3 -> 1.7777778 | J3: Dép. 4 : héberge toute la plateforme. Pén. 4 : contrôle hyperviseur et stockage. Mat. 3 : politique de sécurité globale supposée (H23), qualification à vérifier (H14). Conf. 3 : relation contractuelle claire.
A4: Fournisseur | B4: Éditeur de l'ERP/CRM (mises à jour, télémaintenance) | C4: 4 | D4: 3 | E4: 3 | F4: 3 | G4: =C4*D4 -> 12 | H4: =E4*F4 -> 9 | I4: =G4/H4 -> 1.3333333 | J4: Dép. 4 : ERP non substituable à court terme. Pén. 3 : accès admin au serveur d'application en télémaintenance (H17). Mat. 3, Conf. 3 : éditeur établi.
A5: Prestataire | B5: Transporteurs (fichiers d'expédition, portail de suivi) | C5: 2 | D5: 1 | E5: 2 | F5: 2 | G5: =C5*D5 -> 2 | H5: =E5*F5 -> 4 | I5: =G5/H5 -> 0.5 | J5: Dép. 2 : transporteurs substituables. Pén. 1 : échanges de fichiers, aucun accès au SI. Mat. 2 : grands transporteurs nationaux dotés d'une politique de sécurité (H22). Conf. 2 : intentions neutres.
A6: Partenaire | B6: Cabinet d'expertise comptable (accès distant à la comptabilité) | C6: 2 | D6: 2 | E6: 2 | F6: 3 | G6: =C6*D6 -> 4 | H6: =E6*F6 -> 6 | I6: =G6/H6 -> 0.66666667 | J6: Dép. 2 : utile (clôture, déclarations). Pén. 2 : compte distant sur l'ERP en lecture et export (H18). Mat. 2 : petit cabinet, sécurité réactive. Conf. 3 : relation ancienne.
A7: Client | B7: Grands comptes (commandes par e-mail et EDI) | C7: 3 | D7: 1 | E7: 2 | F7: 3 | G7: =C7*D7 -> 3 | H7: =E7*F7 -> 6 | I7: =G7/H7 -> 0.5 | J7: Dép. 3 : indispensables mais nombreux. Pén. 1 : aucun accès au SI. Mat. 2 : hétérogène. Conf. 3 : intentions positives.
A8: Fournisseur | B8: Plateforme de dématérialisation des factures (PDP) | C8: 3 | D8: 1 | E8: 3 | F8: 3 | G8: =C8*D8 -> 3 | H8: =E8*F8 -> 9 | I8: =G8/H8 -> 0.33333333 | J8: Dép. 3 : obligatoire pour la facturation électronique. Pén. 1 : échange de flux, pas d'accès. Mat. 3 : plateforme immatriculée par l'État. Conf. 3.
A9: Fournisseur | B9: Fournisseur de messagerie en ligne (SaaS) | C9: 3 | D9: 1 | E9: 4 | F9: 3 | G9: =C9*D9 -> 3 | H9: =E9*F9 -> 12 | I9: =G9/H9 -> 0.25 | J9: Dép. 3 : messagerie indispensable. Pén. 1 : pas d'accès à l'ERP. Mat. 4 : grand fournisseur cloud. Conf. 3.
A10: Partenaire | B10: Banque (virements, prélèvements, relevés) | C10: 3 | D10: 1 | E10: 4 | F10: 4 | G10: =C10*D10 -> 3 | H10: =E10*F10 -> 16 | I10: =G10/H10 -> 0.1875 | J10: Dép. 3 : substituable. Pén. 1 : aucun accès au SI. Mat. 4, Conf. 4 : secteur régulé.

Sheet Atelier 3 - Carto PP
C39: Zone veille | D39: Zone CTRL | E39: Zone ALRT | F39: Cercle 1 | G39: Cercle 2 | H39: Cercle 3 | I39: Cercle 4 | J39: Cercle 5
C40: 0 | D40: 0.9 | E40: 3 | F40: 0 | G40: 1 | H40: 2 | I40: 3 | J40: 4

Sheet Atelier 3 - SS
A1: Sources de risques | B1: Objectifs visés | C1: Chemins d'attaque stratégiques | D1: Gravité
A2: SS1 - SR1 Organisation criminelle (rançongiciel) | B2: OV1 - Gain financier : rançon après chiffrement de l'ERP/CRM et des sauvegardes, double extorsion | C2: L'attaquant compromet l'INFOGÉRANT (hameçonnage d'un technicien, VPN d'administration sans MFA, compte admin partagé). Avec ces accès, il prend le contrôle de l'annuaire et des serveurs, exfiltre les données ERP/CRM, puis chiffre l'ERP et supprime les sauvegardes et instantanés via la console de l'HÉBERGEUR IaaS. ER atteints : perte définitive des données (G4), ERP indisponible (G3), vol du fichier clients (G3). | D2: G4
A3: SS2 - SR1 Organisation criminelle (rançongiciel) | B3: OV1 - Gain financier : rançon après chiffrement de l'ERP/CRM | C3: L'attaquant compromet l'ÉDITEUR de l'ERP (compte de télémaintenance ou mise à jour piégée). Il obtient un accès administrateur au serveur d'application et chiffre l'ERP. Sans droits sur l'annuaire ni sur les sauvegardes, la restauration reste possible mais longue : faute de test de restauration documenté (H07), la reconstruction du serveur et la réinstallation de l'ERP avec l'éditeur dépasseraient une semaine [H]. ER atteint : prise de commandes impossible plus d'une semaine (G3). | D3: G3
A4: SS3 - SR1 Organisation criminelle (rançongiciel) | B4: OV1 - Gain financier : rançon après chiffrement de l'ERP/CRM et des sauvegardes | C4: L'attaquant hameçonne un salarié (commercial nomade ou comptable) et prend la main sur son poste. Il élève ses privilèges dans l'annuaire jusqu'à administrateur du domaine, puis chiffre les serveurs ERP/CRM et les sauvegardes hébergées sur la même infrastructure (H08). Chemin direct, sans partie prenante. ER atteints : perte définitive des données (G4), ERP indisponible (G3). | D4: G4
A5: SS4 - SR2 Organisation criminelle (fraude financière) | B5: OV2 - Gain financier : détourner les paiements clients | C5: L'attaquant compromet la messagerie d'un comptable ou d'un commercial (hameçonnage, pas de MFA). Il observe les échanges, puis envoie de fausses factures ou un faux changement de RIB aux grands comptes, qui sont les victimes de la fraude et non un intermédiaire, ou modifie le RIB dans l'ERP avec le compte volé. ER atteint : fraude au RIB (G3). | D5: G3
A6: SS5 - SR3 Collaborateur malveillant (commercial sur le départ) | B6: OV3 - Emporter le fichier clients et les tarifs chez un concurrent | C6: Le commercial utilise ses droits légitimes sur le CRM pour exporter tout le fichier clients et les conditions tarifaires (droits trop larges, aucun contrôle des exports). Il les copie sur une clé USB ou les envoie vers une messagerie personnelle avant son départ. ER atteint : vol et divulgation du fichier clients (G3). | D6: G3

Sheet Atelier 3 - SS1

Sheet Atelier 4 - SO
A1: Chemin d'attaque stratégique associé au scénario opérationnel | B1: Vraissemblance globale
A2: SO1 (SS1 - rançongiciel via l'infogérant) Connaître : Reconnaissance externe : identification de l'infogérant et de ses techniciens Rentrer : Compromission de l'infogérant, puis connexion par son accès distant d'administration Trouver : Prise de contrôle de l'annuaire et des serveurs ERP/CRM Exploiter : Exfiltration des données, chiffrement de l'ERP/CRM, suppression des sauvegardes et instantanés Biens supports : Accès distant d'administration de l'infogérant, annuaire, serveurs d'application, base de données, système de sauvegarde, console IaaS | B2: V3 - Très vraisemblable
A3: SO2 (SS2 - rançongiciel via l'éditeur de l'ERP) Connaître : Reconnaissance externe : identification de l'éditeur de l'ERP Rentrer : Compromission de l'éditeur (accès de télémaintenance ou mise à jour piégée) Trouver : Accès administrateur au serveur d'application ERP Exploiter : Chiffrement de l'ERP ; sauvegardes et annuaire non atteints Biens supports : Module Ventes et Facturation de l'ERP, serveurs d'application | B3: V2 - Vraisemblable
A4: SO3 (SS3 - rançongiciel via hameçonnage d'un salarié) Connaître : Collecte d'informations publiques sur les salariés Rentrer : Hameçonnage d'un salarié et prise de contrôle de son poste Trouver : Élévation de privilèges jusqu'à administrateur du domaine, déplacement vers les serveurs Exploiter : Chiffrement de l'ERP/CRM et des sauvegardes hébergées sur la même infrastructure Biens supports : Postes de travail (ADV, portables des commerciaux), annuaire, serveurs d'application, base de données, système de sauvegarde | B4: V3 - Très vraisemblable
A5: SO4 (SS4 - fraude au RIB) Connaître : Identification des comptables et des grands comptes Rentrer : Compromission d'une boîte de messagerie par hameçonnage Trouver : Observation des échanges de facturation Exploiter : Envoi de fausses factures ou d'un faux changement de RIB aux clients Biens supports : Messagerie, module Facturation de l'ERP, postes de la comptabilité | B5: V3 - Très vraisemblable
A6: SO5 (SS5 - export du fichier clients par un commercial) Connaître : Connaissance interne du CRM et des données de valeur Rentrer : Accès légitime au CRM avec ses propres identifiants Trouver : Repérage du fichier clients et des tarifs négociés Exploiter : Export massif puis sortie des données hors de l'entreprise Biens supports : Application CRM, portables des commerciaux, base de données | B6: V3 - Très vraisemblable

Sheet Atelier 4 - SO1

Sheet Atelier 5 - Risques
A1: Index | B1: Risque | C1: Risque | D1: Traitement | E1: Sources de risque | F1: Objectifs visés | G1: Evennements redoutés | H1: Scénarios stratégiques | I1: Chemin d'attaque | J1: Gravité | K1: Scénarios opérationnels | L1: Vraisemblance
A2: R1 | B2: Un groupe cybercriminel provoque la perte définitive des données de gestion de Rhénalis, en passant par l’infogérant, afin d’exiger une rançon. | C2: Elevé | D2: Réduire | E2: SR1 | F2: OV1 | G2: Perte définitive des données comptables (G4) | H2: SS1 | I2: via l’infogérant | J2: 4 | K2: SO1 | L2: 3
A3: R2 | B3: Un groupe cybercriminel rend l’ERP indisponible plus d’une semaine, en passant par l’éditeur du logiciel, afin d’exiger une rançon. | C3: Modéré | D3: Réduire | E3: SR1 | F3: OV1 | G3: Prise de commandes impossible > 1 semaine (G3) | H3: SS2 | I3: via l'éditeur | J3: 3 | K3: SO2 | L3: 2
A4: R3 | B4: Un groupe cybercriminel provoque la perte définitive des données de gestion, à partir du poste d’un salarié piégé par un courriel, afin d’exiger une rançon. | C4: Elevé | D4: Réduire | E4: SR1 | F4: OV1 | G4: Perte définitive des données comptables (G4) | H4: SS3 | I4: chemin direct (salarié) | J4: 4 | K4: SO3 | L4: 3
A5: R4 | B5: Un fraudeur détourne des paiements de clients vers son propre compte en se faisant passer pour Rhénalis auprès des grands comptes. | C5: Modéré | D5: Réduire | E5: SR2 | F5: OV2 | G5: Modification frauduleuse du RIB (G3) | H5: SS4 | I5: chemin direct (messagerie) | J5: 3 | K5: SO4 | L5: 3
A6: R5 | B6: Un commercial sur le départ emporte le fichier clients et les tarifs négociés pour les utiliser chez un concurrent. | C6: Modéré | D6: Réduire | E6: SR3 | F6: OV3 | G6: Vol et divulgation du fichier clients (G3) | H6: SS5 | I6: chemin direct (accès légitime) | J6: 3 | K6: SO5 | L6: 3

Sheet PTR
A1: N° | B1: Groupe | C1: Mesure | D1: Risques traités | E1: Propriétaire | F1: Complexité | G1: Délai (mois) | H1: Échéance | I1: Coût estimé (hypothèse) | J1: Indicateur de réalisation | K1: Priorité | L1: Statut
A2: M01 | B2: Gouvernance | C2: Avenant sécurité au contrat d'infogérance : MFA, comptes nominatifs, journalisation, correctifs des serveurs sous 30 jours, notification d'incident sous 24 h, droit d'audit annuel | D2: R1 | E2: Thomas Weber (DAF) | F2: Moyenne | G2: 3 | H2: 31/01/2027 | I2: 2 k€ (juridique) | J2: Avenant signé | K2: P1 | L2: À lancer
A3: M05 | B3: Gouvernance | C3: Sensibilisation des salariés à l'hameçonnage et campagne d'exercice semestrielle | D3: R3 R4 | E3: Sophie Haas (resp. informatique) | F3: Faible | G3: 3 | H3: 31/01/2027 | I3: 3 k€/an | J3: Taux de clic aux exercices < 10 % | K3: P1 | L3: À lancer
A4: M10 | B4: Gouvernance | C4: Courrier aux grands comptes : Rhénalis ne change jamais de RIB par e-mail ; en cas de doute, rappeler le numéro habituel | D4: R4 | E4: Thomas Weber (DAF) | F4: Faible | G4: 1 | H4: 30/11/2026 | I4: 0 € | J4: % des grands comptes informés (cible 100 %) | K4: P1 | L4: À lancer
A5: M02 | B5: Gouvernance | C5: Rédiger une PSSI simplifiée et désigner formellement un référent sécurité | D5: Tous | E5: Claire Muller (DG) | F5: Moyenne | G5: 6 | H5: 30/04/2027 | I5: Interne (~15 j) | J5: PSSI validée en comité de direction | K5: P2 | L5: À lancer
A6: M03 | B6: Gouvernance | C6: Mise à jour du registre RGPD et procédure de notification à la CNIL sous 72 h | D6: R5 | E6: Thomas Weber (DAF) | F6: Faible | G6: 3 | H6: 31/01/2027 | I6: 0 € | J6: Registre à jour, procédure validée | K6: P2 | L6: À lancer
A7: M04 | B7: Gouvernance | C7: Vérifier la qualification de l'hébergeur IaaS et les clauses de sécurité du contrat d'hébergement | D7: R1 | E7: Thomas Weber (DAF) | F7: Faible | G7: 2 | H7: 31/12/2026 | I7: 0 € | J7: Rapport de vérification remis | K7: P2 | L7: À lancer
A8: M06 | B8: Protection | C8: Authentification multifacteur sur tous les accès distants (administration, VPN nomades), sur la console d'administration IaaS et sur la messagerie | D8: R1 R3 R4 | E8: Sophie Haas (resp. informatique) | F8: Moyenne | G8: 2 | H8: 31/12/2026 | I8: 4 k€/an | J8: % de comptes protégés par MFA (cible 100 %) | K8: P1 | L8: À lancer
A9: M07 | B9: Protection | C9: Bastion d'administration avec comptes nominatifs et enregistrement des sessions ; suppression du compte admin partagé | D9: R1 R2 | E9: Sophie Haas (pilotage) / InfoGest | F9: Élevée | G9: 6 | H9: 30/04/2027 | I9: 15 k€ + 5 k€/an | J9: Aucun compte admin partagé actif | K9: P1 | L9: À lancer
A10: M09 | B10: Protection | C10: Restreindre l'export du CRM à la direction commerciale, revue trimestrielle des droits, blocage des supports USB sur les portables | D10: R5 | E10: Julien Roth (dir. commercial) | F10: Faible | G10: 2 | H10: 31/12/2026 | I10: 1 k€ | J10: Revue des droits faite chaque trimestre | K10: P1 | L10: À lancer
A11: M18 | B11: Protection | C11: Double validation par le DAF de toute modification de RIB dans l'ERP (clients et fournisseurs), avec traçabilité | D11: R4 | E11: Thomas Weber (DAF) | F11: Faible | G11: 1 | H11: 30/11/2026 | I11: 0 € | J11: 100 % des RIB modifiés validés par le DAF | K11: P1 | L11: À lancer
A12: M08 | B12: Protection | C12: Télémaintenance de l'éditeur ouverte uniquement à la demande, via le bastion, après validation interne | D12: R2 | E12: Sophie Haas (resp. informatique) | F12: Faible | G12: 7 | H12: 31/05/2027 | I12: 0 € | J12: 100 % des sessions validées et enregistrées | K12: P2 | L12: À lancer
A13: M11 | B13: Protection | C13: Durcissement de l'annuaire : séparation des comptes d'administration, mots de passe admin uniques | D13: R1 R3 | E13: InfoGest (pilotage Sophie Haas) | F13: Élevée | G13: 9 | H13: 31/07/2027 | I13: 8 k€ | J13: Audit annuaire sans écart critique | K13: P2 | L13: À lancer
... A20: M17 | B20: Résilience | C20: Étudier une cyber-assurance pour transférer le risque financier résiduel | D20: R1 R4 | E20: Thomas Weber (DAF) | F20: Faible | G20: 6 | H20: 30/04/2027 | I20: 5 à 10 k€/an | J20: Décision de la direction | K20: P3 | L20: À lancer

Sheet Risques résiduels
A1: Risque | B1: Gravité initiale | C1: Vraisemblance initiale | D1: Niveau initial | E1: Mesures | F1: Gravité résiduelle | G1: Vraisemblance résiduelle | H1: Niveau résiduel | I1: Décision
A2: R1 | B2: G4 | C2: V3 | D2: Elevé | E2: M01 M04 M06 M07 M11 M13 M15 M16 M17 | F2: G3 | G2: V2 | H2: Modéré | I2: Acceptation proposée à la direction, suivi trimestriel
A3: R2 | B3: G3 | C3: V2 | D3: Modéré | E3: M07 M08 M15 M16 | F3: G3 | G3: V1 | H3: Significatif | I3: Acceptation proposée à la direction
A4: R3 | B4: G4 | C4: V3 | D4: Elevé | E4: M05 M06 M11 M12 M13 M15 M16 M19 | F4: G3 | G4: V2 | H4: Modéré | I4: Acceptation proposée à la direction, suivi trimestriel
A5: R4 | B5: G3 | C5: V3 | D5: Modéré | E5: M05 M06 M10 M17 M18 | F5: G3 | G5: V2 | H5: Modéré | I5: Acceptation proposée à la direction, suivi trimestriel
A6: R5 | B6: G3 | C6: V3 | D6: Modéré | E6: M03 M09 M14 | F6: G3 | G6: V2 | H6: Modéré | I6: Acceptation proposée à la direction, suivi trimestriel
A8: R1 et R3 passent de G4 à G3 grâce à la sauvegarde immuable testée (M15). R4 reste modéré : les mesures M10 et M18 réduisent la fraude sans la supprimer, car le paiement est fait par le client.
A9: Échelle de la feuille Métriques, du plus haut au plus bas : Elevé (4) > Modéré (3) > Significatif (2) > Faible (1).

Sheet Cadre de suivi
A1: Indicateur | B1: Mesure liée | C1: Cible | D1: Fréquence | E1: Responsable
A2: % de comptes à privilèges et d'accès distants protégés par MFA | B2: M06 | C2: 100 % | D2: Mensuelle | E2: Sophie Haas
A3: Tests de restauration réussis | B3: M15 | C3: 4 par an | D3: Trimestrielle | E3: Sophie Haas
A4: Taux de clic aux exercices d'hameçonnage | B4: M05 | C4: < 10 % | D4: Semestrielle | E4: Sophie Haas
A5: Comptes administrateurs partagés encore actifs | B5: M07 | C5: 0 | D5: Mensuelle | E5: InfoGest / Sophie Haas
A6: Avancement du PTR (actions terminées / prévues) | B6: Toutes | C6: 100 % au 31/10/2027 | D6: Trimestrielle | E6: Claire Muller
A7: RIB modifiés dans l'ERP validés par le DAF | B7: M18 | C7: 100 % | D7: Mensuelle | E7: Thomas Weber
A8: Grands comptes informés de la procédure RIB | B8: M10 | C8: 100 % | D8: Annuelle | E8: Thomas Weber
A9: Postes à jour des correctifs depuis moins de 30 jours | B9: M19 | C9: ≥ 95 % | D9: Mensuelle | E9: Sophie Haas
A11: Gouvernance du suivi
A12: Comité sécurité trimestriel (DG, DAF, resp. informatique, InfoGest) : avancement du PTR et indicateurs.
A13: Revue du cycle opérationnel (atelier 4 et PTR) : annuelle, ou après tout incident significatif.
A14: Revue du cycle stratégique (ateliers 1, 2, 3, 5) : tous les 3 ans, ou en cas de changement majeur (ERP, infogérant, hébergeur).
A15: Prochaine revue complète : octobre 2027.

Sheet datacartoPP
A1: Série 1 | B1: Série 2 | C1: Série 3 | D1: Cercle 1 | E1: Cercle 2 | F1: Cercle 3 | G1: Cercle 4 | H1: Cercle 5
A2: ='Atelier 3 - Carto PP'!C40 -> 0 | B2: ='Atelier 3 - Carto PP'!D40 -> 0.9 | C2: ='Atelier 3 - Carto PP'!E40 -> 3 | D2: ='Atelier 3 - Carto PP'!F40 -> 0 | E2: ='Atelier 3 - Carto PP'!G40 -> 1 | F2: ='Atelier 3 - Carto PP'!H40 -> 2 | G2: ='Atelier 3 - Carto PP'!I40 -> 3 | H2: ='Atelier 3 - Carto PP'!J40 -> 4
A3: =A2 -> 0 | B3: =B2 -> 0.9 | C3: =C2 -> 3 | D3: =D2 -> 0 | E3: =E2 -> 1 | F3: =F2 -> 2 | G3: =G2 -> 3 | H3: =H2 -> 4
A4: =A3 -> 0 | B4: =B3 -> 0.9 | C4: =C3 -> 3 | D4: =D3 -> 0 | E4: =E3 -> 1 | F4: =F3 -> 2 | G4: =G3 -> 3 | H4: =H3 -> 4
A5: =A4 -> 0 | B5: =B4 -> 0.9 | C5: =C4 -> 3 | D5: =D4 -> 0 | E5: =E4 -> 1 | F5: =F4 -> 2 | G5: =G4 -> 3 | H5: =H4 -> 4
A6: =A5 -> 0 | B6: =B5 -> 0.9 | C6: =C5 -> 3 | D6: =D5 -> 0 | E6: =E5 -> 1 | F6: =F5 -> 2 | G6: =G5 -> 3 | H6: =H5 -> 4
A7: =A6 -> 0 | B7: =B6 -> 0.9 | C7: =C6 -> 3 | D7: =D6 -> 0 | E7: =E6 -> 1 | F7: =F6 -> 2 | G7: =G6 -> 3 | H7: =H6 -> 4
A8: =A7 -> 0 | B8: =B7 -> 0.9 | C8: =C7 -> 3 | D8: =D7 -> 0 | E8: =E7 -> 1 | F8: =F7 -> 2 | G8: =G7 -> 3 | H8: =H7 -> 4
A9: =A8 -> 0 | B9: =B8 -> 0.9 | C9: =C8 -> 3 | D9: =D8 -> 0 | E9: =E8 -> 1 | F9: =F8 -> 2 | G9: =G8 -> 3 | H9: =H8 -> 4
A10: =A9 -> 0 | B10: =B9 -> 0.9 | C10: =C9 -> 3 | D10: =D9 -> 0 | E10: =E9 -> 1 | F10: =F9 -> 2 | G10: =G9 -> 3 | H10: =H9 -> 4
A11: =A10 -> 0 | B11: =B10 -> 0.9 | C11: =C10 -> 3 | D11: =D10 -> 0 | E11: =E10 -> 1 | F11: =F10 -> 2 | G11: =G10 -> 3 | H11: =H10 -> 4
A12: =A11 -> 0 | B12: =B11 -> 0.9 | C12: =C11 -> 3 | D12: =D11 -> 0 | E12: =E11 -> 1 | F12: =F11 -> 2 | G12: =G11 -> 3 | H12: =H11 -> 4
A13: =A12 -> 0 | B13: =B12 -> 0.9 | C13: =C12 -> 3 | D13: =D12 -> 0 | E13: =E12 -> 1 | F13: =F12 -> 2 | G13: =G12 -> 3 | H13: =H12 -> 4
A14: =A13 -> 0 | B14: =B13 -> 0.9 | C14: =C13 -> 3 | D14: =D13 -> 0 | E14: =E13 -> 1 | F14: =F13 -> 2 | G14: =G13 -> 3 | H14: =H13 -> 4
... A360: =A359 -> 0 | B360: =B359 -> 0.9 | C360: =C359 -> 3 | D360: =D359 -> 0 | E360: =E359 -> 1 | F360: =F359 -> 2 | G360: =G359 -> 3 | H360: =H359 -> 4
A361: Pour redimensionner la plage de données du graphique, faites glisser le coin inférieur droit de la plage.
